coalpy/__init__.py
coalpy/gpu.cp310-win_amd64.pyd
coalpy/gpu.cp311-win_amd64.pyd
coalpy/gpu.cp312-win_amd64.pyd
coalpy/gpu.cp39-win_amd64.pyd
coalpy/examples/__init.__.py
coalpy/examples/appendconsume.py
coalpy/examples/demo0.py
coalpy/examples/seascape.hlsl
coalpy/examples/seascape.py
coalpy/examples/testInclude.hlsl
coalpy/examples/testShader.hlsl
coalpy/examples/data/test.jpg
coalpy/examples/data/test.png
coalpy/resources/WinPixEventRuntime.dll
coalpy/resources/dxcompiler.dll
coalpy/resources/dxil.dll
coalpy/resources/libdxcompiler.so
coalpy/utils/__init__.py
coalpy/utils/profiler.py
coalpy-0.55.dist-info/LICENSE
coalpy-0.55.dist-info/METADATA
coalpy-0.55.dist-info/WHEEL
coalpy-0.55.dist-info/top_level.txt
coalpy-0.55.dist-info/RECORD
