Metadata-Version: 2.1
Name: coalpy
Version: 0.55
Summary: CoalPy - Compute Abstraction Layer for Python.
Home-page: https://github.com/kecho/coalpy
Author: Kleber A Garcia
Author-email: kecho_garcia@hotmail.com
License: MIT
Project-URL: Bug Tracker, https://github.com/kecho/coalpy/issues
Classifier: Programming Language :: Python :: 3
Classifier: License :: OSI Approved :: MIT License
Classifier: Operating System :: Microsoft :: Windows
Requires-Python: >=3.10
License-File: LICENSE
